scytheautoupdate/__init__.py
scytheautoupdate/scythe_auto_update.py
scytheautoupdate-0.0.3.dist-info/LICENSE
scytheautoupdate-0.0.3.dist-info/METADATA
scytheautoupdate-0.0.3.dist-info/WHEEL
scytheautoupdate-0.0.3.dist-info/top_level.txt
scytheautoupdate-0.0.3.dist-info/RECORD
