Metadata-Version: 2.1
Name: scytheautoupdate
Version: 0.0.3
Summary: A package to check for and auto update github repositiores
Author-email: Dark_Eden <darkedenc9@gmail.com>
Project-URL: Homepage, https://github.com/DarkEden-coding/scytheautoupdate
Project-URL: Bug Tracker, https://github.com/DarkEden-coding/scytheautoupdate/issues
Classifier: Programming Language :: Python :: 3
Classifier: License :: OSI Approved :: MIT License
Classifier: Operating System :: OS Independent
Requires-Python: >=3.7
License-File: LICENSE
